{
    "_comment": "https://confluence/display/TRAC/User+Experience+Designer",

    "type": "User Experience Designer",
    "version": "1.0.0",

    "id": "",
    "name": "",
    "updated": "",

    "sections": {
        "User Experience Design": {
            "competencies": {
                "D1": {
                    "category": "Skill",
                    "competency": "Develop wireframes/sketches/user flows and prototypes describing how user will interact with the product",
                    "examples": {
                        "0": "Limited experience or knowledge. May have some familiarity but no hands-on or professional experience.",
                        "1": "Has some experience or knowledge. Can perform with limited oversight and guidance.",
                        "2": "Has production-level experience and deep hands-on knowledge. Can effectively share knowledge and assist others.",
                        "3": "Expert-level. Fully autonomous and can deliver consistently with an exceptional degree of quality."
                    },
                    "rating": "",
                    "comment": ""
                },
                "D2": {
                    "category": "Skill",
                    "competency": "Uses brand elements to create the visual representation of the product",
                    "examples": {
                        "0": "Limited experience or knowledge. May have some familiarity but no hands-on or professional experience.",
                        "1": "Has some experience or knowledge. Can perform with limited oversight and guidance.",
                        "2": "Has production-level experience and deep hands-on knowledge. Can effectively share knowledge and assist others.",
                        "3": "Expert-level. Fully autonomous and can deliver consistently with an exceptional degree of quality."
                    },
                    "rating": "",
                    "comment": ""
                },
                "D3": {
                    "category": "Skill",
                    "competency": "Receive input from UX research to help solve user problems",
                    "examples": {
                        "0": "Limited experience or knowledge. May have some familiarity but no hands-on or professional experience.",
                        "1": "Has some experience or knowledge. Can perform with limited oversight and guidance.",
                        "2": "Has production-level experience and deep hands-on knowledge. Can effectively share knowledge and assist others.",
                        "3": "Expert-level. Fully autonomous and can deliver consistently with an exceptional degree of quality."
                    },
                    "rating": "",
                    "comment": ""
                },
                "D4": {
                    "category": "Skill",
                    "competency": "Strong working knowledge of Adobe Creative Suite",
                    "examples": {
                        "0": "Limited experience or knowledge. May have some familiarity but no hands-on or professional experience.",
                        "1": "Has some experience or knowledge. Can perform with limited oversight and guidance.",
                        "2": "Has production-level experience and deep hands-on knowledge. Can effectively share knowledge and assist others.",
                        "3": "Expert-level. Fully autonomous and can deliver consistently with an exceptional degree of quality."
                    },
                    "rating": "",
                    "comment": ""
                },
                "D5": {
                    "category": "Skill",
                    "competency": "Research interaction design and technology trends",
                    "examples": {
                        "0": "Limited experience or knowledge. May have some familiarity but no hands-on or professional experience.",
                        "1": "Has some experience or knowledge. Can perform with limited oversight and guidance.",
                        "2": "Has production-level experience and deep hands-on knowledge. Can effectively share knowledge and assist others.",
                        "3": "Expert-level. Fully autonomous and can deliver consistently with an exceptional degree of quality."
                    },
                    "rating": "",
                    "comment": ""
                },
                "D6": {
                    "category": "Skill",
                    "competency": "Implements design standards and ensures a consistent design language is applied across products",
                    "examples": {
                        "0": "Limited experience or knowledge. May have some familiarity but no hands-on or professional experience.",
                        "1": "Has some experience or knowledge. Can perform with limited oversight and guidance.",
                        "2": "Has production-level experience and deep hands-on knowledge. Can effectively share knowledge and assist others.",
                        "3": "Expert-level. Fully autonomous and can deliver consistently with an exceptional degree of quality."
                    },
                    "rating": "",
                    "comment": ""
                },
                "D7": {
                    "category": "Skill",
                    "competency": "Create a cohesive style/pattern guide and provide guidance on it's application across products",
                    "examples": {
                        "0": "Limited experience or knowledge. May have some familiarity but no hands-on or professional experience.",
                        "1": "Has some experience or knowledge. Can perform with limited oversight and guidance.",
                        "2": "Has production-level experience and deep hands-on knowledge. Can effectively share knowledge and assist others.",
                        "3": "Expert-level. Fully autonomous and can deliver consistently with an exceptional degree of quality."
                    },
                    "rating": "",
                    "comment": ""
                },
                "D8": {
                    "category": "Skill",
                    "competency": "Facilitate whiteboard/ideation/working sessions with dev team ",
                    "examples": {
                        "0": "Limited experience or knowledge. May have some familiarity but no hands-on or professional experience.",
                        "1": "Has some experience or knowledge. Can perform with limited oversight and guidance.",
                        "2": "Has production-level experience and deep hands-on knowledge. Can effectively share knowledge and assist others.",
                        "3": "Expert-level. Fully autonomous and can deliver consistently with an exceptional degree of quality."
                    },
                    "rating": "",
                    "comment": ""
                }
            }
        },
        "Advocate for and Know the User": {
            "competencies": {
                "U1": {
                    "category": "Skill",
                    "competency": "Speaks up for what's right for the client to anyone and is able to explain why it is important",
                    "examples": {
                        "0": "Limited experience or knowledge. May have some familiarity but no hands-on or professional experience.",
                        "1": "Has some experience or knowledge. Can perform with limited oversight and guidance.",
                        "2": "Has production-level experience and deep hands-on knowledge. Can effectively share knowledge and assist others.",
                        "3": "Expert-level. Fully autonomous and can deliver consistently with an exceptional degree of quality."
                    },
                    "rating": "",
                    "comment": ""
                },
                "U2": {
                    "category": "Skill",
                    "competency": "Actively shadows areas of the business and utilizes Mousetrap input to help solve user problems",
                    "examples": {
                        "0": "Limited experience or knowledge. May have some familiarity but no hands-on or professional experience.",
                        "1": "Has some experience or knowledge. Can perform with limited oversight and guidance.",
                        "2": "Has production-level experience and deep hands-on knowledge. Can effectively share knowledge and assist others.",
                        "3": "Expert-level. Fully autonomous and can deliver consistently with an exceptional degree of quality."
                    },
                    "rating": "",
                    "comment": ""
                }
            }
        },
        "Communication": {
            "competencies": {
                "C1": {
                    "category": "Skill",
                    "competency": "Understands and applies basic communication skills (tone, physiology, words) to get the desired message across in writing, over the phone, and in person",
                    "examples": {
                        "0": "Limited experience or knowledge. May have some familiarity but no hands-on or professional experience.",
                        "1": "Has some experience or knowledge. Can perform with limited oversight and guidance.",
                        "2": "Has production-level experience and deep hands-on knowledge. Can effectively share knowledge and assist others.",
                        "3": "Expert-level. Fully autonomous and can deliver consistently with an exceptional degree of quality."
                    },
                    "rating": "",
                    "comment": ""
                },
                "C2": {
                    "category": "Skill",
                    "competency": "Makes impactful changes from feedback, and works with team leader to develop realistic personal career and development path",
                    "examples": {
                        "0": "Limited experience or knowledge. May have some familiarity but no hands-on or professional experience.",
                        "1": "Has some experience or knowledge. Can perform with limited oversight and guidance.",
                        "2": "Has production-level experience and deep hands-on knowledge. Can effectively share knowledge and assist others.",
                        "3": "Expert-level. Fully autonomous and can deliver consistently with an exceptional degree of quality."
                    },
                    "rating": "",
                    "comment": ""
                },
                "C3": {
                    "category": "Skill",
                    "competency": "Actively listens and asks key questions to understand impact and gather needs",
                    "examples": {
                        "0": "Limited experience or knowledge. May have some familiarity but no hands-on or professional experience.",
                        "1": "Has some experience or knowledge. Can perform with limited oversight and guidance.",
                        "2": "Has production-level experience and deep hands-on knowledge. Can effectively share knowledge and assist others.",
                        "3": "Expert-level. Fully autonomous and can deliver consistently with an exceptional degree of quality."
                    },
                    "rating": "",
                    "comment": ""
                },
                "C4": {
                    "category": "Skill",
                    "competency": "Able to communicate with and present to end users, fellow team members and leaders",
                    "examples": {
                        "0": "Limited experience or knowledge. May have some familiarity but no hands-on or professional experience.",
                        "1": "Has some experience or knowledge. Can perform with limited oversight and guidance.",
                        "2": "Has production-level experience and deep hands-on knowledge. Can effectively share knowledge and assist others.",
                        "3": "Expert-level. Fully autonomous and can deliver consistently with an exceptional degree of quality."
                    },
                    "rating": "",
                    "comment": ""
                },
                "C5": {
                    "category": "Skill",
                    "competency": "Organizes meetings that have a clear purpose, an agenda, adequate coverage, proper frequency, and timeliness. Ensures that all team members are engaged and have a chance to contribute",
                    "examples": {
                        "0": "Limited experience or knowledge. May have some familiarity but no hands-on or professional experience.",
                        "1": "Has some experience or knowledge. Can perform with limited oversight and guidance.",
                        "2": "Has production-level experience and deep hands-on knowledge. Can effectively share knowledge and assist others.",
                        "3": "Expert-level. Fully autonomous and can deliver consistently with an exceptional degree of quality."
                    },
                    "rating": "",
                    "comment": ""
                },
                "C6": {
                    "category": "Skill",
                    "competency": "Capable of professionally handling and encouraging positive conflict",
                    "examples": {
                        "0": "Limited experience or knowledge. May have some familiarity but no hands-on or professional experience.",
                        "1": "Has some experience or knowledge. Can perform with limited oversight and guidance.",
                        "2": "Has production-level experience and deep hands-on knowledge. Can effectively share knowledge and assist others.",
                        "3": "Expert-level. Fully autonomous and can deliver consistently with an exceptional degree of quality."
                    },
                    "rating": "",
                    "comment": ""
                },
                "C7": {
                    "category": "Skill",
                    "competency": "Delivers constructive feedback without negativity",
                    "examples": {
                        "0": "Limited experience or knowledge. May have some familiarity but no hands-on or professional experience.",
                        "1": "Has some experience or knowledge. Can perform with limited oversight and guidance.",
                        "2": "Has production-level experience and deep hands-on knowledge. Can effectively share knowledge and assist others.",
                        "3": "Expert-level. Fully autonomous and can deliver consistently with an exceptional degree of quality."
                    },
                    "rating": "",
                    "comment": ""
                },
                "C8": {
                    "category": "Skill",
                    "competency": "Organizes and leads programs and presentations to promote best practices and standards",
                    "examples": {
                        "0": "Limited experience or knowledge. May have some familiarity but no hands-on or professional experience.",
                        "1": "Has some experience or knowledge. Can perform with limited oversight and guidance.",
                        "2": "Has production-level experience and deep hands-on knowledge. Can effectively share knowledge and assist others.",
                        "3": "Expert-level. Fully autonomous and can deliver consistently with an exceptional degree of quality."
                    },
                    "rating": "",
                    "comment": ""
                },
                "C9": {
                    "category": "Skill",
                    "competency": "Provides visibility and proactive communication across the organization including senior leaders and executive leadership. Filters the noise and amplifies important information.",
                    "examples": {
                        "0": "Limited experience or knowledge. May have some familiarity but no hands-on or professional experience.",
                        "1": "Has some experience or knowledge. Can perform with limited oversight and guidance.",
                        "2": "Has production-level experience and deep hands-on knowledge. Can effectively share knowledge and assist others.",
                        "3": "Expert-level. Fully autonomous and can deliver consistently with an exceptional degree of quality."
                    },
                    "rating": "",
                    "comment": ""
                },
                "C10": {
                    "category": "Skill",
                    "competency": "Builds strong relationships and promotes a creative, quality environment",
                    "examples": {
                        "0": "Limited experience or knowledge. May have some familiarity but no hands-on or professional experience.",
                        "1": "Has some experience or knowledge. Can perform with limited oversight and guidance.",
                        "2": "Has production-level experience and deep hands-on knowledge. Can effectively share knowledge and assist others.",
                        "3": "Expert-level. Fully autonomous and can deliver consistently with an exceptional degree of quality."
                    },
                    "rating": "",
                    "comment": ""
                }
            }
        },
        "Culture Promoter": {
            "competencies": {
                "CP1": {
                    "category": "Skill",
                    "competency": "Works well with others and is open to feedback",
                    "examples": {
                        "0": "Limited experience or knowledge. May have some familiarity but no hands-on or professional experience.",
                        "1": "Has some experience or knowledge. Can perform with limited oversight and guidance.",
                        "2": "Has production-level experience and deep hands-on knowledge. Can effectively share knowledge and assist others.",
                        "3": "Expert-level. Fully autonomous and can deliver consistently with an exceptional degree of quality."
                    },
                    "rating": "",
                    "comment": ""
                },
                "CP2": {
                    "category": "Skill",
                    "competency": "Seeks out a mentor and acts on their recommendations",
                    "examples": {
                        "0": "Limited experience or knowledge. May have some familiarity but no hands-on or professional experience.",
                        "1": "Has some experience or knowledge. Can perform with limited oversight and guidance.",
                        "2": "Has production-level experience and deep hands-on knowledge. Can effectively share knowledge and assist others.",
                        "3": "Expert-level. Fully autonomous and can deliver consistently with an exceptional degree of quality."
                    },
                    "rating": "",
                    "comment": ""
                },
                "CP3": {
                    "category": "Skill",
                    "competency": "Manages time effectively",
                    "examples": {
                        "0": "Limited experience or knowledge. May have some familiarity but no hands-on or professional experience.",
                        "1": "Has some experience or knowledge. Can perform with limited oversight and guidance.",
                        "2": "Has production-level experience and deep hands-on knowledge. Can effectively share knowledge and assist others.",
                        "3": "Expert-level. Fully autonomous and can deliver consistently with an exceptional degree of quality."
                    },
                    "rating": "",
                    "comment": ""
                },
                "CP4": {
                    "category": "Skill",
                    "competency": "Displays a positive attitude. Flexible, takes initiative, and demonstrates curiosity and open mindedness",
                    "examples": {
                        "0": "Limited experience or knowledge. May have some familiarity but no hands-on or professional experience.",
                        "1": "Has some experience or knowledge. Can perform with limited oversight and guidance.",
                        "2": "Has production-level experience and deep hands-on knowledge. Can effectively share knowledge and assist others.",
                        "3": "Expert-level. Fully autonomous and can deliver consistently with an exceptional degree of quality."
                    },
                    "rating": "",
                    "comment": ""
                },
                "CP5": {
                    "category": "Skill",
                    "competency": "Readily volunteers to take the conn. Balances multiple tasks with specific due dates, priority, and difficulty",
                    "examples": {
                        "0": "Limited experience or knowledge. May have some familiarity but no hands-on or professional experience.",
                        "1": "Has some experience or knowledge. Can perform with limited oversight and guidance.",
                        "2": "Has production-level experience and deep hands-on knowledge. Can effectively share knowledge and assist others.",
                        "3": "Expert-level. Fully autonomous and can deliver consistently with an exceptional degree of quality."
                    },
                    "rating": "",
                    "comment": ""
                },
                "CP6": {
                    "category": "Skill",
                    "competency": "Ability to work well individually or as part of a team",
                    "examples": {
                        "0": "Limited experience or knowledge. May have some familiarity but no hands-on or professional experience.",
                        "1": "Has some experience or knowledge. Can perform with limited oversight and guidance.",
                        "2": "Has production-level experience and deep hands-on knowledge. Can effectively share knowledge and assist others.",
                        "3": "Expert-level. Fully autonomous and can deliver consistently with an exceptional degree of quality."
                    },
                    "rating": "",
                    "comment": ""
                },
                "CP7": {
                    "category": "Skill",
                    "competency": "Sets high personal standards for self performance and quality",
                    "examples": {
                        "0": "Limited experience or knowledge. May have some familiarity but no hands-on or professional experience.",
                        "1": "Has some experience or knowledge. Can perform with limited oversight and guidance.",
                        "2": "Has production-level experience and deep hands-on knowledge. Can effectively share knowledge and assist others.",
                        "3": "Expert-level. Fully autonomous and can deliver consistently with an exceptional degree of quality."
                    },
                    "rating": "",
                    "comment": ""
                },
                "CP8": {
                    "category": "Skill",
                    "competency": "Reaches out to others and the online community to discover new frontiers",
                    "examples": {
                        "0": "Limited experience or knowledge. May have some familiarity but no hands-on or professional experience.",
                        "1": "Has some experience or knowledge. Can perform with limited oversight and guidance.",
                        "2": "Has production-level experience and deep hands-on knowledge. Can effectively share knowledge and assist others.",
                        "3": "Expert-level. Fully autonomous and can deliver consistently with an exceptional degree of quality."
                    },
                    "rating": "",
                    "comment": ""
                },
                "CP9": {
                    "category": "Skill",
                    "competency": "Actively involved in developing one’s skills by participating in Bullet Time, reading books, following tutorials and is engaged in a technical community",
                    "examples": {
                        "0": "Limited experience or knowledge. May have some familiarity but no hands-on or professional experience.",
                        "1": "Has some experience or knowledge. Can perform with limited oversight and guidance.",
                        "2": "Has production-level experience and deep hands-on knowledge. Can effectively share knowledge and assist others.",
                        "3": "Expert-level. Fully autonomous and can deliver consistently with an exceptional degree of quality."
                    },
                    "rating": "",
                    "comment": ""
                },
                "CP10": {
                    "category": "Skill",
                    "competency": "Builds and maintains trust with all stakeholders",
                    "examples": {
                        "0": "Limited experience or knowledge. May have some familiarity but no hands-on or professional experience.",
                        "1": "Has some experience or knowledge. Can perform with limited oversight and guidance.",
                        "2": "Has production-level experience and deep hands-on knowledge. Can effectively share knowledge and assist others.",
                        "3": "Expert-level. Fully autonomous and can deliver consistently with an exceptional degree of quality."
                    },
                    "rating": "",
                    "comment": ""
                },
                "CP11": {
                    "category": "Skill",
                    "competency": "Regularly gives credit and highlights the successes of others",
                    "examples": {
                        "0": "Limited experience or knowledge. May have some familiarity but no hands-on or professional experience.",
                        "1": "Has some experience or knowledge. Can perform with limited oversight and guidance.",
                        "2": "Has production-level experience and deep hands-on knowledge. Can effectively share knowledge and assist others.",
                        "3": "Expert-level. Fully autonomous and can deliver consistently with an exceptional degree of quality."
                    },
                    "rating": "",
                    "comment": ""
                },
                "CP12": {
                    "category": "Skill",
                    "competency": "Mentors a team member",
                    "examples": {
                        "0": "Limited experience or knowledge. May have some familiarity but no hands-on or professional experience.",
                        "1": "Has some experience or knowledge. Can perform with limited oversight and guidance.",
                        "2": "Has production-level experience and deep hands-on knowledge. Can effectively share knowledge and assist others.",
                        "3": "Expert-level. Fully autonomous and can deliver consistently with an exceptional degree of quality."
                    },
                    "rating": "",
                    "comment": ""
                },
                "CP13": {
                    "category": "Skill",
                    "competency": "Always thinks about who they should be recruiting to work at the company",
                    "examples": {
                        "0": "Limited experience or knowledge. May have some familiarity but no hands-on or professional experience.",
                        "1": "Has some experience or knowledge. Can perform with limited oversight and guidance.",
                        "2": "Has production-level experience and deep hands-on knowledge. Can effectively share knowledge and assist others.",
                        "3": "Expert-level. Fully autonomous and can deliver consistently with an exceptional degree of quality."
                    },
                    "rating": "",
                    "comment": ""
                },
                "CP14": {
                    "category": "Skill",
                    "competency": "Participates in communities in and outside of work, demonstrating the culture of QL Technology ",
                    "examples": {
                        "0": "Limited experience or knowledge. May have some familiarity but no hands-on or professional experience.",
                        "1": "Has some experience or knowledge. Can perform with limited oversight and guidance.",
                        "2": "Has production-level experience and deep hands-on knowledge. Can effectively share knowledge and assist others.",
                        "3": "Expert-level. Fully autonomous and can deliver consistently with an exceptional degree of quality."
                    },
                    "rating": "",
                    "comment": ""
                },
                "CP15": {
                    "category": "Skill",
                    "competency": "Organizes celebrations",
                    "examples": {
                        "0": "Limited experience or knowledge. May have some familiarity but no hands-on or professional experience.",
                        "1": "Has some experience or knowledge. Can perform with limited oversight and guidance.",
                        "2": "Has production-level experience and deep hands-on knowledge. Can effectively share knowledge and assist others.",
                        "3": "Expert-level. Fully autonomous and can deliver consistently with an exceptional degree of quality."
                    },
                    "rating": "",
                    "comment": ""
                },
                "CP16": {
                    "category": "Skill",
                    "competency": "Mentors multiple team members at the same time. Mentoring on concepts/processes, user experiences, and systems across a family of products",
                    "examples": {
                        "0": "Limited experience or knowledge. May have some familiarity but no hands-on or professional experience.",
                        "1": "Has some experience or knowledge. Can perform with limited oversight and guidance.",
                        "2": "Has production-level experience and deep hands-on knowledge. Can effectively share knowledge and assist others.",
                        "3": "Expert-level. Fully autonomous and can deliver consistently with an exceptional degree of quality."
                    },
                    "rating": "",
                    "comment": ""
                }
            }
        },
        "Self Development": {
            "competencies": {
                "SD1": {
                    "category": "Skill",
                    "competency": "Strong time management skills and organizational skills",
                    "examples": {
                        "0": "Limited experience or knowledge. May have some familiarity but no hands-on or professional experience.",
                        "1": "Has some experience or knowledge. Can perform with limited oversight and guidance.",
                        "2": "Has production-level experience and deep hands-on knowledge. Can effectively share knowledge and assist others.",
                        "3": "Expert-level. Fully autonomous and can deliver consistently with an exceptional degree of quality."
                    },
                    "rating": "",
                    "comment": ""
                },
                "SD2": {
                    "category": "Skill",
                    "competency": "Takes criticism well, is a self-corrector and learns from mistakes",
                    "examples": {
                        "0": "Limited experience or knowledge. May have some familiarity but no hands-on or professional experience.",
                        "1": "Has some experience or knowledge. Can perform with limited oversight and guidance.",
                        "2": "Has production-level experience and deep hands-on knowledge. Can effectively share knowledge and assist others.",
                        "3": "Expert-level. Fully autonomous and can deliver consistently with an exceptional degree of quality."
                    },
                    "rating": "",
                    "comment": ""
                },
                "SD3": {
                    "category": "Skill",
                    "competency": "Proactively seeks feedback and is willing to act on feedback for growth opportunities and to gain knowledge ",
                    "examples": {
                        "0": "Limited experience or knowledge. May have some familiarity but no hands-on or professional experience.",
                        "1": "Has some experience or knowledge. Can perform with limited oversight and guidance.",
                        "2": "Has production-level experience and deep hands-on knowledge. Can effectively share knowledge and assist others.",
                        "3": "Expert-level. Fully autonomous and can deliver consistently with an exceptional degree of quality."
                    },
                    "rating": "",
                    "comment": ""
                },
                "SD4": {
                    "category": "Skill",
                    "competency": "Takes ownership in learning about new developments in their field and teaches others. ",
                    "examples": {
                        "0": "Limited experience or knowledge. May have some familiarity but no hands-on or professional experience.",
                        "1": "Has some experience or knowledge. Can perform with limited oversight and guidance.",
                        "2": "Has production-level experience and deep hands-on knowledge. Can effectively share knowledge and assist others.",
                        "3": "Expert-level. Fully autonomous and can deliver consistently with an exceptional degree of quality."
                    },
                    "rating": "",
                    "comment": ""
                },
                "SD5": {
                    "category": "Skill",
                    "competency": "Proactively pursuing and attending conferences, meet-ups, and training's ",
                    "examples": {
                        "0": "Limited experience or knowledge. May have some familiarity but no hands-on or professional experience.",
                        "1": "Has some experience or knowledge. Can perform with limited oversight and guidance.",
                        "2": "Has production-level experience and deep hands-on knowledge. Can effectively share knowledge and assist others.",
                        "3": "Expert-level. Fully autonomous and can deliver consistently with an exceptional degree of quality."
                    },
                    "rating": "",
                    "comment": ""
                },
                "SD6": {
                    "category": "Skill",
                    "competency": "Proactively reading books, articles, and watching videos to learn new things in the UX industry",
                    "examples": {
                        "0": "Limited experience or knowledge. May have some familiarity but no hands-on or professional experience.",
                        "1": "Has some experience or knowledge. Can perform with limited oversight and guidance.",
                        "2": "Has production-level experience and deep hands-on knowledge. Can effectively share knowledge and assist others.",
                        "3": "Expert-level. Fully autonomous and can deliver consistently with an exceptional degree of quality."
                    },
                    "rating": "",
                    "comment": ""
                },
                "SD7": {
                    "category": "Skill",
                    "competency": "Proactively engages in the Detroit area UX & Design communities",
                    "examples": {
                        "0": "Limited experience or knowledge. May have some familiarity but no hands-on or professional experience.",
                        "1": "Has some experience or knowledge. Can perform with limited oversight and guidance.",
                        "2": "Has production-level experience and deep hands-on knowledge. Can effectively share knowledge and assist others.",
                        "3": "Expert-level. Fully autonomous and can deliver consistently with an exceptional degree of quality."
                    },
                    "rating": "",
                    "comment": ""
                },
                "SD8": {
                    "category": "Skill",
                    "competency": "Turns negativity into new challenges and positivity",
                    "examples": {
                        "0": "Limited experience or knowledge. May have some familiarity but no hands-on or professional experience.",
                        "1": "Has some experience or knowledge. Can perform with limited oversight and guidance.",
                        "2": "Has production-level experience and deep hands-on knowledge. Can effectively share knowledge and assist others.",
                        "3": "Expert-level. Fully autonomous and can deliver consistently with an exceptional degree of quality."
                    },
                    "rating": "",
                    "comment": ""
                },
                "SD9": {
                    "category": "Skill",
                    "competency": "Consistently advocating and teaching UX practices within the organization",
                    "examples": {
                        "0": "Limited experience or knowledge. May have some familiarity but no hands-on or professional experience.",
                        "1": "Has some experience or knowledge. Can perform with limited oversight and guidance.",
                        "2": "Has production-level experience and deep hands-on knowledge. Can effectively share knowledge and assist others.",
                        "3": "Expert-level. Fully autonomous and can deliver consistently with an exceptional degree of quality."
                    },
                    "rating": "",
                    "comment": ""
                }
            }
        },
        "Teamwork/Relationship Building": {
            "competencies": {
                "T1": {
                    "category": "Skill",
                    "competency": "Actively develops relationships with development teams, content strategy, creative and other key teams involved in the design process",
                    "examples": {
                        "0": "Limited experience or knowledge. May have some familiarity but no hands-on or professional experience.",
                        "1": "Has some experience or knowledge. Can perform with limited oversight and guidance.",
                        "2": "Has production-level experience and deep hands-on knowledge. Can effectively share knowledge and assist others.",
                        "3": "Expert-level. Fully autonomous and can deliver consistently with an exceptional degree of quality."
                    },
                    "rating": "",
                    "comment": ""
                },
                "T2": {
                    "category": "Skill",
                    "competency": "Recognizes and organizes meetings with the appropriate people to solve problems",
                    "examples": {
                        "0": "Limited experience or knowledge. May have some familiarity but no hands-on or professional experience.",
                        "1": "Has some experience or knowledge. Can perform with limited oversight and guidance.",
                        "2": "Has production-level experience and deep hands-on knowledge. Can effectively share knowledge and assist others.",
                        "3": "Expert-level. Fully autonomous and can deliver consistently with an exceptional degree of quality."
                    },
                    "rating": "",
                    "comment": ""
                },
                "T3": {
                    "category": "Skill",
                    "competency": "Help and encourage others try new things at work",
                    "examples": {
                        "0": "Limited experience or knowledge. May have some familiarity but no hands-on or professional experience.",
                        "1": "Has some experience or knowledge. Can perform with limited oversight and guidance.",
                        "2": "Has production-level experience and deep hands-on knowledge. Can effectively share knowledge and assist others.",
                        "3": "Expert-level. Fully autonomous and can deliver consistently with an exceptional degree of quality."
                    },
                    "rating": "",
                    "comment": ""
                },
                "T4": {
                    "category": "Skill",
                    "competency": "Advanced skill level for what would be expected of a team members with their experience and frequently shares their best practices to help develop others",
                    "examples": {
                        "0": "Limited experience or knowledge. May have some familiarity but no hands-on or professional experience.",
                        "1": "Has some experience or knowledge. Can perform with limited oversight and guidance.",
                        "2": "Has production-level experience and deep hands-on knowledge. Can effectively share knowledge and assist others.",
                        "3": "Expert-level. Fully autonomous and can deliver consistently with an exceptional degree of quality."
                    },
                    "rating": "",
                    "comment": ""
                },
                "T5": {
                    "category": "Skill",
                    "competency": "Can evaluate who has what talent and utilizes bench appropriately",
                    "examples": {
                        "0": "Limited experience or knowledge. May have some familiarity but no hands-on or professional experience.",
                        "1": "Has some experience or knowledge. Can perform with limited oversight and guidance.",
                        "2": "Has production-level experience and deep hands-on knowledge. Can effectively share knowledge and assist others.",
                        "3": "Expert-level. Fully autonomous and can deliver consistently with an exceptional degree of quality."
                    },
                    "rating": "",
                    "comment": ""
                },
                "T6": {
                    "category": "Skill",
                    "competency": "Creates a vision and a purpose for what others do",
                    "examples": {
                        "0": "Limited experience or knowledge. May have some familiarity but no hands-on or professional experience.",
                        "1": "Has some experience or knowledge. Can perform with limited oversight and guidance.",
                        "2": "Has production-level experience and deep hands-on knowledge. Can effectively share knowledge and assist others.",
                        "3": "Expert-level. Fully autonomous and can deliver consistently with an exceptional degree of quality."
                    },
                    "rating": "",
                    "comment": ""
                },
                "T7": {
                    "category": "Skill",
                    "competency": "Drives the mission of the Team",
                    "examples": {
                        "0": "Limited experience or knowledge. May have some familiarity but no hands-on or professional experience.",
                        "1": "Has some experience or knowledge. Can perform with limited oversight and guidance.",
                        "2": "Has production-level experience and deep hands-on knowledge. Can effectively share knowledge and assist others.",
                        "3": "Expert-level. Fully autonomous and can deliver consistently with an exceptional degree of quality."
                    },
                    "rating": "",
                    "comment": ""
                }
            }
        }
    }
}
